{
  "pagination": {
    "page": 14,
    "pageTotal": 29,
    "size": 100,
    "total": 2851
  },
  "items": [
    {
      "actualRank": 1301,
      "personId": "2023THON12",
      "personName": "Hoàng Trung Thông",
      "avgKinchScore": 3.3759673257707035,
      "kinchScore": {
        "222": 22.304283604135893,
        "333": 16.613878491217967,
        "444": 0,
        "555": 0,
        "666": 0,
        "777": 0,
        "333oh": 0,
        "333bf": 0,
        "333fm": 0,
        "333mbf": 0,
        "444bf": 0,
        "555bf": 0,
        "clock": 0,
        "minx": 0,
        "pyram": 18.473282442748094,
        "skewb": 0,
        "sq1": 0
      }
    },
    {
      "actualRank": 1302,
      "personId": "2018KHOA05",
      "personName": "Nguyễn Đăng Khoa",
      "avgKinchScore": 3.37586859484984,
      "kinchScore": {
        "222": 20.684931506849317,
        "333": 36.704834605597966,
        "444": 0,
        "555": 0,
        "666": 0,
        "777": 0,
        "333oh": 0,
        "333bf": 0,
        "333fm": 0,
        "333mbf": 0,
        "444bf": 0,
        "555bf": 0,
        "clock": 0,
        "minx": 0,
        "pyram": 0,
        "skewb": 0,
        "sq1": 0
      }
    },
    {
      "actualRank": 1303,
      "personId": "2022NAMP02",
      "personName": "Phan Hải Nam",
      "avgKinchScore": 3.373487948002844,
      "kinchScore": {
        "222": 0,
        "333": 39.01284651791751,
        "444": 0,
        "555": 0,
        "666": 0,
        "777": 0,
        "333oh": 18.336448598130843,
        "333bf": 0,
        "333fm": 0,
        "333mbf": 0,
        "444bf": 0,
        "555bf": 0,
        "clock": 0,
        "minx": 0,
        "pyram": 0,
        "skewb": 0,
        "sq1": 0
      }
    },
    {
      "actualRank": 1304,
      "personId": "2025DANG04",
      "personName": "Hoàng Hải Đăng",
      "avgKinchScore": 3.3710140644144366,
      "kinchScore": {
        "222": 18.618988902589393,
        "333": 22.7344365642238,
        "444": 0,
        "555": 0,
        "666": 0,
        "777": 0,
        "333oh": 15.953813628232233,
        "333bf": 0,
        "333fm": 0,
        "333mbf": 0,
        "444bf": 0,
        "555bf": 0,
        "clock": 0,
        "minx": 0,
        "pyram": 0,
        "skewb": 0,
        "sq1": 0
      }
    },
    {
      "actualRank": 1305,
      "personId": "2023MINH12",
      "personName": "Trịnh Ngọc Minh",
      "avgKinchScore": 3.3669220457285793,
      "kinchScore": {
        "222": 26.773049645390074,
        "333": 30.464625131995778,
        "444": 0,
        "555": 0,
        "666": 0,
        "777": 0,
        "333oh": 0,
        "333bf": 0,
        "333fm": 0,
        "333mbf": 0,
        "444bf": 0,
        "555bf": 0,
        "clock": 0,
        "minx": 0,
        "pyram": 0,
        "skewb": 0,
        "sq1": 0
      }
    },
    {
      "actualRank": 1306,
      "personId": "2018HUYP02",
      "personName": "Phạm Quốc Huy",
      "avgKinchScore": 3.3665965937343563,
      "kinchScore": {
        "222": 0,
        "333": 23.85283174865647,
        "444": 0,
        "555": 0,
        "666": 0,
        "777": 0,
        "333oh": 0,
        "333bf": 0,
        "333fm": 0,
        "333mbf": 0,
        "444bf": 0,
        "555bf": 0,
        "clock": 0,
        "minx": 0,
        "pyram": 33.37931034482759,
        "skewb": 0,
        "sq1": 0
      }
    },
    {
      "actualRank": 1307,
      "personId": "2025KHAN15",
      "personName": "Nguyễn Minh Khang",
      "avgKinchScore": 3.3662677420105553,
      "kinchScore": {
        "222": 23.85466034755134,
        "333": 33.371891266628104,
        "444": 0,
        "555": 0,
        "666": 0,
        "777": 0,
        "333oh": 0,
        "333bf": 0,
        "333fm": 0,
        "333mbf": 0,
        "444bf": 0,
        "555bf": 0,
        "clock": 0,
        "minx": 0,
        "pyram": 0,
        "skewb": 0,
        "sq1": 0
      }
    },
    {
      "actualRank": 1308,
      "personId": "2025NGUY04",
      "personName": "Alex Nguyen",
      "avgKinchScore": 3.364479752964846,
      "kinchScore": {
        "222": 17.51740139211137,
        "333": 22.779313067508884,
        "444": 0,
        "555": 0,
        "666": 0,
        "777": 0,
        "333oh": 0,
        "333bf": 0,
        "333fm": 0,
        "333mbf": 0,
        "444bf": 0,
        "555bf": 0,
        "clock": 0,
        "minx": 0,
        "pyram": 16.899441340782122,
        "skewb": 0,
        "sq1": 0
      }
    },
    {
      "actualRank": 1309,
      "personId": "2020LINH01",
      "personName": "Nguyễn Đức Vĩnh Linh",
      "avgKinchScore": 3.36166388290549,
      "kinchScore": {
        "222": 0,
        "333": 36.357908002520475,
        "444": 0,
        "555": 0,
        "666": 0,
        "777": 0,
        "333oh": 0,
        "333bf": 0,
        "333fm": 0,
        "333mbf": 0,
        "444bf": 0,
        "555bf": 0,
        "clock": 0,
        "minx": 0,
        "pyram": 20.790378006872853,
        "skewb": 0,
        "sq1": 0
      }
    },
    {
      "actualRank": 1310,
      "personId": "2012NGAN01",
      "personName": "Trần Thị Thu Ngân",
      "avgKinchScore": 3.3577789553569732,
      "kinchScore": {
        "222": 15.945089757127773,
        "333": 24.26408746846089,
        "444": 0,
        "555": 0,
        "666": 0,
        "777": 0,
        "333oh": 16.873065015479877,
        "333bf": 0,
        "333fm": 0,
        "333mbf": 0,
        "444bf": 0,
        "555bf": 0,
        "clock": 0,
        "minx": 0,
        "pyram": 0,
        "skewb": 0,
        "sq1": 0
      }
    },
    {
      "actualRank": 1311,
      "personId": "2016ANHN04",
      "personName": "Nguyễn Hữu Anh",
      "avgKinchScore": 3.3564087137328373,
      "kinchScore": {
        "222": 24.23756019261637,
        "333": 32.821387940841866,
        "444": 0,
        "555": 0,
        "666": 0,
        "777": 0,
        "333oh": 0,
        "333bf": 0,
        "333fm": 0,
        "333mbf": 0,
        "444bf": 0,
        "555bf": 0,
        "clock": 0,
        "minx": 0,
        "pyram": 0,
        "skewb": 0,
        "sq1": 0
      }
    },
    {
      "actualRank": 1312,
      "personId": "2024SANG07",
      "personName": "Bùi Đặng Minh Sang",
      "avgKinchScore": 3.3527046794883684,
      "kinchScore": {
        "222": 15.945089757127773,
        "333": 22.689736531655523,
        "444": 0,
        "555": 0,
        "666": 0,
        "777": 0,
        "333oh": 0,
        "333bf": 0,
        "333fm": 0,
        "333mbf": 0,
        "444bf": 0,
        "555bf": 0,
        "clock": 0,
        "minx": 0,
        "pyram": 18.361153262518968,
        "skewb": 0,
        "sq1": 0
      }
    },
    {
      "actualRank": 1313,
      "personId": "2022BAOV02",
      "personName": "Võ Lê Duy Bảo",
      "avgKinchScore": 3.3488720020641893,
      "kinchScore": {
        "222": 0,
        "333": 28.980411853340033,
        "444": 0,
        "555": 0,
        "666": 0,
        "777": 0,
        "333oh": 0,
        "333bf": 0,
        "333fm": 0,
        "333mbf": 0,
        "444bf": 0,
        "555bf": 0,
        "clock": 0,
        "minx": 0,
        "pyram": 16.101131071190952,
        "skewb": 11.849281110560238,
        "sq1": 0
      }
    },
    {
      "actualRank": 1314,
      "personId": "2018BAON02",
      "personName": "Nguyen Minh Bao",
      "avgKinchScore": 3.3433100853858386,
      "kinchScore": {
        "222": 23.48367029548989,
        "333": 33.35260115606937,
        "444": 0,
        "555": 0,
        "666": 0,
        "777": 0,
        "333oh": 0,
        "333bf": 0,
        "333fm": 0,
        "333mbf": 0,
        "444bf": 0,
        "555bf": 0,
        "clock": 0,
        "minx": 0,
        "pyram": 0,
        "skewb": 0,
        "sq1": 0
      }
    },
    {
      "actualRank": 1315,
      "personId": "2012HANG02",
      "personName": "Đỗ Lê Hùng",
      "avgKinchScore": 3.33656917748228,
      "kinchScore": {
        "222": 0,
        "333": 37.08226221079691,
        "444": 19.63941380640185,
        "555": 0,
        "666": 0,
        "777": 0,
        "333oh": 0,
        "333bf": 0,
        "333fm": 0,
        "333mbf": 0,
        "444bf": 0,
        "555bf": 0,
        "clock": 0,
        "minx": 0,
        "pyram": 0,
        "skewb": 0,
        "sq1": 0
      }
    },
    {
      "actualRank": 1316,
      "personId": "2022HIEU09",
      "personName": "Trần Xuân Hiếu",
      "avgKinchScore": 3.335396680774297,
      "kinchScore": {
        "222": 19.973544973544975,
        "333": 36.728198599618075,
        "444": 0,
        "555": 0,
        "666": 0,
        "777": 0,
        "333oh": 0,
        "333bf": 0,
        "333fm": 0,
        "333mbf": 0,
        "444bf": 0,
        "555bf": 0,
        "clock": 0,
        "minx": 0,
        "pyram": 0,
        "skewb": 0,
        "sq1": 0
      }
    },
    {
      "actualRank": 1317,
      "personId": "2018TUAN05",
      "personName": "Trần Mạnh Tuấn",
      "avgKinchScore": 3.3349247074757593,
      "kinchScore": {
        "222": 21.207865168539325,
        "333": 35.485854858548585,
        "444": 0,
        "555": 0,
        "666": 0,
        "777": 0,
        "333oh": 0,
        "333bf": 0,
        "333fm": 0,
        "333mbf": 0,
        "444bf": 0,
        "555bf": 0,
        "clock": 0,
        "minx": 0,
        "pyram": 0,
        "skewb": 0,
        "sq1": 0
      }
    },
    {
      "actualRank": 1318,
      "personId": "2023LAMP03",
      "personName": "Phạm Chí Lâm",
      "avgKinchScore": 3.3332124604802433,
      "kinchScore": {
        "222": 16.87150837988827,
        "333": 39.793103448275865,
        "444": 0,
        "555": 0,
        "666": 0,
        "777": 0,
        "333oh": 0,
        "333bf": 0,
        "333fm": 0,
        "333mbf": 0,
        "444bf": 0,
        "555bf": 0,
        "clock": 0,
        "minx": 0,
        "pyram": 0,
        "skewb": 0,
        "sq1": 0
      }
    },
    {
      "actualRank": 1319,
      "personId": "2024ANDA01",
      "personName": "Đặng Hoàng An",
      "avgKinchScore": 3.330035259228548,
      "kinchScore": {
        "222": 13.096270598438856,
        "333": 43.51432880844646,
        "444": 0,
        "555": 0,
        "666": 0,
        "777": 0,
        "333oh": 0,
        "333bf": 0,
        "333fm": 0,
        "333mbf": 0,
        "444bf": 0,
        "555bf": 0,
        "clock": 0,
        "minx": 0,
        "pyram": 0,
        "skewb": 0,
        "sq1": 0
      }
    },
    {
      "actualRank": 1320,
      "personId": "2018KHAN23",
      "personName": "Lê Hoàng Nam Khánh",
      "avgKinchScore": 3.328894103192626,
      "kinchScore": {
        "222": 10.633802816901408,
        "333": 20.395899611170023,
        "444": 0,
        "555": 0,
        "666": 0,
        "777": 0,
        "333oh": 0,
        "333bf": 0,
        "333fm": 0,
        "333mbf": 0,
        "444bf": 0,
        "555bf": 0,
        "clock": 0,
        "minx": 0,
        "pyram": 0,
        "skewb": 25.56149732620321,
        "sq1": 0
      }
    },
    {
      "actualRank": 1321,
      "personId": "2023KHAN50",
      "personName": "Nguyễn Văn Khánh",
      "avgKinchScore": 3.3278576570257847,
      "kinchScore": {
        "222": 0,
        "333": 0,
        "444": 0,
        "555": 56.573580169438344,
        "666": 0,
        "777": 0,
        "333oh": 0,
        "333bf": 0,
        "333fm": 0,
        "333mbf": 0,
        "444bf": 0,
        "555bf": 0,
        "clock": 0,
        "minx": 0,
        "pyram": 0,
        "skewb": 0,
        "sq1": 0
      }
    },
    {
      "actualRank": 1322,
      "personId": "2016DUYN03",
      "personName": "Nguyễn Bá Khánh Duy",
      "avgKinchScore": 3.3262281457566445,
      "kinchScore": {
        "222": 23.85466034755134,
        "333": 32.69121813031162,
        "444": 0,
        "555": 0,
        "666": 0,
        "777": 0,
        "333oh": 0,
        "333bf": 0,
        "333fm": 0,
        "333mbf": 0,
        "444bf": 0,
        "555bf": 0,
        "clock": 0,
        "minx": 0,
        "pyram": 0,
        "skewb": 0,
        "sq1": 0
      }
    },
    {
      "actualRank": 1323,
      "personId": "2023VUPH01",
      "personName": "Phạm Huy Vũ",
      "avgKinchScore": 3.311351607896692,
      "kinchScore": {
        "222": 27.911275415896487,
        "333": 28.381701918347268,
        "444": 0,
        "555": 0,
        "666": 0,
        "777": 0,
        "333oh": 0,
        "333bf": 0,
        "333fm": 0,
        "333mbf": 0,
        "444bf": 0,
        "555bf": 0,
        "clock": 0,
        "minx": 0,
        "pyram": 0,
        "skewb": 0,
        "sq1": 0
      }
    },
    {
      "actualRank": 1324,
      "personId": "2024THIN03",
      "personName": "Bùi Ngọc Thịnh",
      "avgKinchScore": 3.3052392353586426,
      "kinchScore": {
        "222": 21.388101983002834,
        "333": 34.80096501809409,
        "444": 0,
        "555": 0,
        "666": 0,
        "777": 0,
        "333oh": 0,
        "333bf": 0,
        "333fm": 0,
        "333mbf": 0,
        "444bf": 0,
        "555bf": 0,
        "clock": 0,
        "minx": 0,
        "pyram": 0,
        "skewb": 0,
        "sq1": 0
      }
    },
    {
      "actualRank": 1325,
      "personId": "2018HIEU02",
      "personName": "Lê Minh Hiếu",
      "avgKinchScore": 3.30236043995784,
      "kinchScore": {
        "222": 24.592833876221498,
        "333": 31.54729360306178,
        "444": 0,
        "555": 0,
        "666": 0,
        "777": 0,
        "333oh": 0,
        "333bf": 0,
        "333fm": 0,
        "333mbf": 0,
        "444bf": 0,
        "555bf": 0,
        "clock": 0,
        "minx": 0,
        "pyram": 0,
        "skewb": 0,
        "sq1": 0
      }
    },
    {
      "actualRank": 1326,
      "personId": "2023LONG21",
      "personName": "Lê Minh Long",
      "avgKinchScore": 3.289017876828263,
      "kinchScore": {
        "222": 13.327449249779347,
        "333": 26.79981421272643,
        "444": 0,
        "555": 0,
        "666": 0,
        "777": 0,
        "333oh": 0,
        "333bf": 0,
        "333fm": 0,
        "333mbf": 0,
        "444bf": 0,
        "555bf": 0,
        "clock": 0,
        "minx": 0,
        "pyram": 15.78604044357469,
        "skewb": 0,
        "sq1": 0
      }
    },
    {
      "actualRank": 1327,
      "personId": "2018THAN01",
      "personName": "Bùi Đức Thắng",
      "avgKinchScore": 3.2805301139911003,
      "kinchScore": {
        "222": 22.740963855421686,
        "333": 33.02804808242702,
        "444": 0,
        "555": 0,
        "666": 0,
        "777": 0,
        "333oh": 0,
        "333bf": 0,
        "333fm": 0,
        "333mbf": 0,
        "444bf": 0,
        "555bf": 0,
        "clock": 0,
        "minx": 0,
        "pyram": 0,
        "skewb": 0,
        "sq1": 0
      }
    },
    {
      "actualRank": 1328,
      "personId": "2022YCAO01",
      "personName": "Cao Thị Ngọc Ý",
      "avgKinchScore": 3.2761753349988645,
      "kinchScore": {
        "222": 0,
        "333": 55.6949806949807,
        "444": 0,
        "555": 0,
        "666": 0,
        "777": 0,
        "333oh": 0,
        "333bf": 0,
        "333fm": 0,
        "333mbf": 0,
        "444bf": 0,
        "555bf": 0,
        "clock": 0,
        "minx": 0,
        "pyram": 0,
        "skewb": 0,
        "sq1": 0
      }
    },
    {
      "actualRank": 1329,
      "personId": "2020HUNG02",
      "personName": "Nguyễn Xuân Hưng",
      "avgKinchScore": 3.270751967780844,
      "kinchScore": {
        "222": 0,
        "333": 40.3214535290007,
        "444": 0,
        "555": 0,
        "666": 0,
        "777": 0,
        "333oh": 0,
        "333bf": 0,
        "333fm": 0,
        "333mbf": 0,
        "444bf": 0,
        "555bf": 0,
        "clock": 0,
        "minx": 0,
        "pyram": 0,
        "skewb": 15.281329923273656,
        "sq1": 0
      }
    },
    {
      "actualRank": 1330,
      "personId": "2017ANHH01",
      "personName": "Hứa Nam Anh",
      "avgKinchScore": 3.2706982805558487,
      "kinchScore": {
        "222": 0,
        "333": 30.496828752642706,
        "444": 0,
        "555": 0,
        "666": 0,
        "777": 0,
        "333oh": 0,
        "333bf": 0,
        "333fm": 0,
        "333mbf": 0,
        "444bf": 0,
        "555bf": 0,
        "clock": 0,
        "minx": 0,
        "pyram": 0,
        "skewb": 25.10504201680672,
        "sq1": 0
      }
    },
    {
      "actualRank": 1331,
      "personId": "2019HUNG15",
      "personName": "Đinh Phúc Hưng",
      "avgKinchScore": 3.263574660633484,
      "kinchScore": {
        "222": 0,
        "333": 55.48076923076923,
        "444": 0,
        "555": 0,
        "666": 0,
        "777": 0,
        "333oh": 0,
        "333bf": 0,
        "333fm": 0,
        "333mbf": 0,
        "444bf": 0,
        "555bf": 0,
        "clock": 0,
        "minx": 0,
        "pyram": 0,
        "skewb": 0,
        "sq1": 0
      }
    },
    {
      "actualRank": 1332,
      "personId": "2018TRUN01",
      "personName": "Nguyen Hieu Trung",
      "avgKinchScore": 3.2587587924477504,
      "kinchScore": {
        "222": 21.852387843704776,
        "333": 33.54651162790698,
        "444": 0,
        "555": 0,
        "666": 0,
        "777": 0,
        "333oh": 0,
        "333bf": 0,
        "333fm": 0,
        "333mbf": 0,
        "444bf": 0,
        "555bf": 0,
        "clock": 0,
        "minx": 0,
        "pyram": 0,
        "skewb": 0,
        "sq1": 0
      }
    },
    {
      "actualRank": 1333,
      "personId": "2018THIN01",
      "personName": "Âu Dương Hữu Thịnh",
      "avgKinchScore": 3.2537790106190907,
      "kinchScore": {
        "222": 26.260869565217394,
        "333": 29.053373615307148,
        "444": 0,
        "555": 0,
        "666": 0,
        "777": 0,
        "333oh": 0,
        "333bf": 0,
        "333fm": 0,
        "333mbf": 0,
        "444bf": 0,
        "555bf": 0,
        "clock": 0,
        "minx": 0,
        "pyram": 0,
        "skewb": 0,
        "sq1": 0
      }
    },
    {
      "actualRank": 1334,
      "personId": "2018NGUY31",
      "personName": "Nguyễn Trần Thảo Nguyên",
      "avgKinchScore": 3.2503247333256233,
      "kinchScore": {
        "222": 13.904235727440147,
        "333": 22.2693940563489,
        "444": 0,
        "555": 0,
        "666": 0,
        "777": 0,
        "333oh": 19.081890682746547,
        "333bf": 0,
        "333fm": 0,
        "333mbf": 0,
        "444bf": 0,
        "555bf": 0,
        "clock": 0,
        "minx": 0,
        "pyram": 0,
        "skewb": 0,
        "sq1": 0
      }
    },
    {
      "actualRank": 1335,
      "personId": "2022LUAN03",
      "personName": "Nguyen Ba Hoang Luan",
      "avgKinchScore": 3.245475695425734,
      "kinchScore": {
        "222": 0,
        "333": 29.08266129032258,
        "444": 0,
        "555": 0,
        "666": 0,
        "777": 0,
        "333oh": 26.090425531914896,
        "333bf": 0,
        "333fm": 0,
        "333mbf": 0,
        "444bf": 0,
        "555bf": 0,
        "clock": 0,
        "minx": 0,
        "pyram": 0,
        "skewb": 0,
        "sq1": 0
      }
    },
    {
      "actualRank": 1336,
      "personId": "2024NGUY05",
      "personName": "Thao My Ngoc Nguyen",
      "avgKinchScore": 3.2409608281532685,
      "kinchScore": {
        "222": 13.084922010398614,
        "333": 24.584576054537706,
        "444": 0,
        "555": 0,
        "666": 0,
        "777": 0,
        "333oh": 0,
        "333bf": 0,
        "333fm": 0,
        "333mbf": 0,
        "444bf": 0,
        "555bf": 0,
        "clock": 0,
        "minx": 0,
        "pyram": 7.7663671373555845,
        "skewb": 9.660468876313661,
        "sq1": 0
      }
    },
    {
      "actualRank": 1337,
      "personId": "2022SONH01",
      "personName": "Hoàng Sơn",
      "avgKinchScore": 3.2353255335078224,
      "kinchScore": {
        "222": 17.081447963800905,
        "333": 23.331985442782045,
        "444": 0,
        "555": 0,
        "666": 0,
        "777": 0,
        "333oh": 0,
        "333bf": 0,
        "333fm": 0,
        "333mbf": 0,
        "444bf": 0,
        "555bf": 0,
        "clock": 0,
        "minx": 0,
        "pyram": 14.587100663050029,
        "skewb": 0,
        "sq1": 0
      }
    },
    {
      "actualRank": 1338,
      "personId": "2019TRIE01",
      "personName": "Lê Minh Triết",
      "avgKinchScore": 3.234012347535371,
      "kinchScore": {
        "222": 18.734491315136477,
        "333": 36.243718592964825,
        "444": 0,
        "555": 0,
        "666": 0,
        "777": 0,
        "333oh": 0,
        "333bf": 0,
        "333fm": 0,
        "333mbf": 0,
        "444bf": 0,
        "555bf": 0,
        "clock": 0,
        "minx": 0,
        "pyram": 0,
        "skewb": 0,
        "sq1": 0
      }
    },
    {
      "actualRank": 1339,
      "personId": "2025PHUC03",
      "personName": "Pham Si Phuc",
      "avgKinchScore": 3.2334712332793925,
      "kinchScore": {
        "222": 0,
        "333": 32.09121245828698,
        "444": 0,
        "555": 0,
        "666": 0,
        "777": 0,
        "333oh": 22.87779850746269,
        "333bf": 0,
        "333fm": 0,
        "333mbf": 0,
        "444bf": 0,
        "555bf": 0,
        "clock": 0,
        "minx": 0,
        "pyram": 0,
        "skewb": 0,
        "sq1": 0
      }
    },
    {
      "actualRank": 1340,
      "personId": "2017KHOA10",
      "personName": "Đỗ Ngọc Đăng Khoa",
      "avgKinchScore": 3.233010508014802,
      "kinchScore": {
        "222": 20.160213618157545,
        "333": 34.80096501809409,
        "444": 0,
        "555": 0,
        "666": 0,
        "777": 0,
        "333oh": 0,
        "333bf": 0,
        "333fm": 0,
        "333mbf": 0,
        "444bf": 0,
        "555bf": 0,
        "clock": 0,
        "minx": 0,
        "pyram": 0,
        "skewb": 0,
        "sq1": 0
      }
    },
    {
      "actualRank": 1341,
      "personId": "2010NGUY46",
      "personName": "Phuc Nguyen",
      "avgKinchScore": 3.2316540566384853,
      "kinchScore": {
        "222": 10.48611111111111,
        "333": 18.505452212957024,
        "444": 12.23203026481715,
        "555": 0,
        "666": 0,
        "777": 0,
        "333oh": 13.714525373968964,
        "333bf": 0,
        "333fm": 0,
        "333mbf": 0,
        "444bf": 0,
        "555bf": 0,
        "clock": 0,
        "minx": 0,
        "pyram": 0,
        "skewb": 0,
        "sq1": 0
      }
    },
    {
      "actualRank": 1342,
      "personId": "2024NGHI03",
      "personName": "Bùi Đại Nghĩa",
      "avgKinchScore": 3.2294173616163877,
      "kinchScore": {
        "222": 0,
        "333": 54.90009514747859,
        "444": 0,
        "555": 0,
        "666": 0,
        "777": 0,
        "333oh": 0,
        "333bf": 0,
        "333fm": 0,
        "333mbf": 0,
        "444bf": 0,
        "555bf": 0,
        "clock": 0,
        "minx": 0,
        "pyram": 0,
        "skewb": 0,
        "sq1": 0
      }
    },
    {
      "actualRank": 1343,
      "personId": "2017NAMV01",
      "personName": "Võ Nhật Nam",
      "avgKinchScore": 3.229125008079088,
      "kinchScore": {
        "222": 17.062146892655367,
        "333": 26.899766899766895,
        "444": 0,
        "555": 0,
        "666": 0,
        "777": 0,
        "333oh": 0,
        "333bf": 0,
        "333fm": 0,
        "333mbf": 0,
        "444bf": 0,
        "555bf": 0,
        "clock": 0,
        "minx": 0,
        "pyram": 0,
        "skewb": 10.933211344922231,
        "sq1": 0
      }
    },
    {
      "actualRank": 1344,
      "personId": "2016HUYL01",
      "personName": "Lâm Gia Huy",
      "avgKinchScore": 3.2260831228290554,
      "kinchScore": {
        "222": 20.741758241758244,
        "333": 34.1016548463357,
        "444": 0,
        "555": 0,
        "666": 0,
        "777": 0,
        "333oh": 0,
        "333bf": 0,
        "333fm": 0,
        "333mbf": 0,
        "444bf": 0,
        "555bf": 0,
        "clock": 0,
        "minx": 0,
        "pyram": 0,
        "skewb": 0,
        "sq1": 0
      }
    },
    {
      "actualRank": 1345,
      "personId": "2018ANHT02",
      "personName": "Trần Lê Quốc Anh",
      "avgKinchScore": 3.221170241666522,
      "kinchScore": {
        "222": 18.45965770171149,
        "333": 25,
        "444": 0,
        "555": 0,
        "666": 0,
        "777": 0,
        "333oh": 0,
        "333bf": 0,
        "333fm": 0,
        "333mbf": 0,
        "444bf": 0,
        "555bf": 0,
        "clock": 0,
        "minx": 0,
        "pyram": 0,
        "skewb": 11.300236406619385,
        "sq1": 0
      }
    },
    {
      "actualRank": 1346,
      "personId": "2024KHAN14",
      "personName": "Phan Minh Khang",
      "avgKinchScore": 3.220225471592812,
      "kinchScore": {
        "222": 0,
        "333": 54.743833017077804,
        "444": 0,
        "555": 0,
        "666": 0,
        "777": 0,
        "333oh": 0,
        "333bf": 0,
        "333fm": 0,
        "333mbf": 0,
        "444bf": 0,
        "555bf": 0,
        "clock": 0,
        "minx": 0,
        "pyram": 0,
        "skewb": 0,
        "sq1": 0
      }
    },
    {
      "actualRank": 1347,
      "personId": "2022VANN03",
      "personName": "Nguyễn Thế Văn",
      "avgKinchScore": 3.2173266450417772,
      "kinchScore": {
        "222": 21.947674418604652,
        "333": 32.74687854710556,
        "444": 0,
        "555": 0,
        "666": 0,
        "777": 0,
        "333oh": 0,
        "333bf": 0,
        "333fm": 0,
        "333mbf": 0,
        "444bf": 0,
        "555bf": 0,
        "clock": 0,
        "minx": 0,
        "pyram": 0,
        "skewb": 0,
        "sq1": 0
      }
    },
    {
      "actualRank": 1348,
      "personId": "2016DUNG03",
      "personName": "Trần Quốc Dũng",
      "avgKinchScore": 3.2168385512982325,
      "kinchScore": {
        "222": 16.52078774617068,
        "333": 20.755395683453237,
        "444": 0,
        "555": 0,
        "666": 0,
        "777": 0,
        "333oh": 0,
        "333bf": 0,
        "333fm": 0,
        "333mbf": 0,
        "444bf": 0,
        "555bf": 0,
        "clock": 0,
        "minx": 0,
        "pyram": 17.41007194244604,
        "skewb": 0,
        "sq1": 0
      }
    },
    {
      "actualRank": 1349,
      "personId": "2022NAMD01",
      "personName": "Đào Nguyễn Sơn Nam",
      "avgKinchScore": 3.21467264714349,
      "kinchScore": {
        "222": 12.774957698815568,
        "333": 23.637853338795576,
        "444": 0,
        "555": 0,
        "666": 0,
        "777": 0,
        "333oh": 0,
        "333bf": 0,
        "333fm": 0,
        "333mbf": 0,
        "444bf": 0,
        "555bf": 0,
        "clock": 0,
        "minx": 0,
        "pyram": 18.236623963828183,
        "skewb": 0,
        "sq1": 0
      }
    },
    {
      "actualRank": 1350,
      "personId": "2023KHAN10",
      "personName": "Bùi Trần Tuấn Khang",
      "avgKinchScore": 3.21382414192485,
      "kinchScore": {
        "222": 0,
        "333": 36.0625,
        "444": 0,
        "555": 0,
        "666": 0,
        "777": 0,
        "333oh": 18.572510412722455,
        "333bf": 0,
        "333fm": 0,
        "333mbf": 0,
        "444bf": 0,
        "555bf": 0,
        "clock": 0,
        "minx": 0,
        "pyram": 0,
        "skewb": 0,
        "sq1": 0
      }
    },
    {
      "actualRank": 1351,
      "personId": "2022NAMP01",
      "personName": "Phạm Hải Nam",
      "avgKinchScore": 3.2085736779881886,
      "kinchScore": {
        "222": 18.347509113001216,
        "333": 36.19824341279799,
        "444": 0,
        "555": 0,
        "666": 0,
        "777": 0,
        "333oh": 0,
        "333bf": 0,
        "333fm": 0,
        "333mbf": 0,
        "444bf": 0,
        "555bf": 0,
        "clock": 0,
        "minx": 0,
        "pyram": 0,
        "skewb": 0,
        "sq1": 0
      }
    },
    {
      "actualRank": 1352,
      "personId": "2023NAMN06",
      "personName": "Nguyễn Phuong Nam",
      "avgKinchScore": 3.199986167633233,
      "kinchScore": {
        "222": 15.14543630892678,
        "333": 21.98095238095238,
        "444": 0,
        "555": 0,
        "666": 0,
        "777": 0,
        "333oh": 0,
        "333bf": 0,
        "333fm": 0,
        "333mbf": 0,
        "444bf": 0,
        "555bf": 0,
        "clock": 0,
        "minx": 0,
        "pyram": 17.273376159885796,
        "skewb": 0,
        "sq1": 0
      }
    },
    {
      "actualRank": 1353,
      "personId": "2010MAIT01",
      "personName": "Thai Tung Mai",
      "avgKinchScore": 3.1999433800447963,
      "kinchScore": {
        "222": 23.410852713178297,
        "333": 30.98818474758324,
        "444": 0,
        "555": 0,
        "666": 0,
        "777": 0,
        "333oh": 0,
        "333bf": 0,
        "333fm": 0,
        "333mbf": 0,
        "444bf": 0,
        "555bf": 0,
        "clock": 0,
        "minx": 0,
        "pyram": 0,
        "skewb": 0,
        "sq1": 0
      }
    },
    {
      "actualRank": 1354,
      "personId": "2016NGUY25",
      "personName": "Vũ Hải Nguyên",
      "avgKinchScore": 3.1980851993138892,
      "kinchScore": {
        "222": 19.712793733681462,
        "333": 34.65465465465466,
        "444": 0,
        "555": 0,
        "666": 0,
        "777": 0,
        "333oh": 0,
        "333bf": 0,
        "333fm": 0,
        "333mbf": 0,
        "444bf": 0,
        "555bf": 0,
        "clock": 0,
        "minx": 0,
        "pyram": 0,
        "skewb": 0,
        "sq1": 0
      }
    },
    {
      "actualRank": 1355,
      "personId": "2016ANHH01",
      "personName": "Hoàng Anh",
      "avgKinchScore": 3.197710600502226,
      "kinchScore": {
        "222": 19.433719433719435,
        "333": 34.9273607748184,
        "444": 0,
        "555": 0,
        "666": 0,
        "777": 0,
        "333oh": 0,
        "333bf": 0,
        "333fm": 0,
        "333mbf": 0,
        "444bf": 0,
        "555bf": 0,
        "clock": 0,
        "minx": 0,
        "pyram": 0,
        "skewb": 0,
        "sq1": 0
      }
    },
    {
      "actualRank": 1356,
      "personId": "2024BAOV01",
      "personName": "Võ Quốc Bảo",
      "avgKinchScore": 3.1970122256470965,
      "kinchScore": {
        "222": 24.044585987261147,
        "333": 30.304621848739494,
        "444": 0,
        "555": 0,
        "666": 0,
        "777": 0,
        "333oh": 0,
        "333bf": 0,
        "333fm": 0,
        "333mbf": 0,
        "444bf": 0,
        "555bf": 0,
        "clock": 0,
        "minx": 0,
        "pyram": 0,
        "skewb": 0,
        "sq1": 0
      }
    },
    {
      "actualRank": 1357,
      "personId": "2023LAMN02",
      "personName": "Nguyễn Bá Lâm",
      "avgKinchScore": 3.1968358520912763,
      "kinchScore": {
        "222": 20.54421768707483,
        "333": 33.80199179847686,
        "444": 0,
        "555": 0,
        "666": 0,
        "777": 0,
        "333oh": 0,
        "333bf": 0,
        "333fm": 0,
        "333mbf": 0,
        "444bf": 0,
        "555bf": 0,
        "clock": 0,
        "minx": 0,
        "pyram": 0,
        "skewb": 0,
        "sq1": 0
      }
    },
    {
      "actualRank": 1358,
      "personId": "2022LONG12",
      "personName": "Vũ Thành Long",
      "avgKinchScore": 3.196073176316097,
      "kinchScore": {
        "222": 19.260204081632654,
        "333": 21.545929798356983,
        "444": 0,
        "555": 0,
        "666": 0,
        "777": 0,
        "333oh": 0,
        "333bf": 0,
        "333fm": 0,
        "333mbf": 0,
        "444bf": 0,
        "555bf": 0,
        "clock": 0,
        "minx": 0,
        "pyram": 13.527110117384014,
        "skewb": 0,
        "sq1": 0
      }
    },
    {
      "actualRank": 1359,
      "personId": "2023HUYN10",
      "personName": "Nguyễn Hữu Huy",
      "avgKinchScore": 3.189332664534871,
      "kinchScore": {
        "222": 24.552845528455283,
        "333": 29.66580976863753,
        "444": 0,
        "555": 0,
        "666": 0,
        "777": 0,
        "333oh": 0,
        "333bf": 0,
        "333fm": 0,
        "333mbf": 0,
        "444bf": 0,
        "555bf": 0,
        "clock": 0,
        "minx": 0,
        "pyram": 0,
        "skewb": 0,
        "sq1": 0
      }
    },
    {
      "actualRank": 1360,
      "personId": "2023ANVA01",
      "personName": "Văn Ân",
      "avgKinchScore": 3.186373213747076,
      "kinchScore": {
        "222": 0,
        "333": 34.696331930246544,
        "444": 0,
        "555": 0,
        "666": 0,
        "777": 0,
        "333oh": 19.47201270345375,
        "333bf": 0,
        "333fm": 0,
        "333mbf": 0,
        "444bf": 0,
        "555bf": 0,
        "clock": 0,
        "minx": 0,
        "pyram": 0,
        "skewb": 0,
        "sq1": 0
      }
    },
    {
      "actualRank": 1361,
      "personId": "2018MINH19",
      "personName": "Nguyễn Ngọc Minh",
      "avgKinchScore": 3.1744590542153106,
      "kinchScore": {
        "222": 25.7679180887372,
        "333": 24.01165210153974,
        "444": 0,
        "555": 0,
        "666": 0,
        "777": 0,
        "333oh": 0,
        "333bf": 0,
        "333fm": 0,
        "333mbf": 0,
        "444bf": 0,
        "555bf": 0,
        "clock": 4.186233731383336,
        "minx": 0,
        "pyram": 0,
        "skewb": 0,
        "sq1": 0
      }
    },
    {
      "actualRank": 1362,
      "personId": "2020LONG06",
      "personName": "Đào Tiến Long",
      "avgKinchScore": 3.170300261648924,
      "kinchScore": {
        "222": 21.47937411095306,
        "333": 32.41573033707865,
        "444": 0,
        "555": 0,
        "666": 0,
        "777": 0,
        "333oh": 0,
        "333bf": 0,
        "333fm": 0,
        "333mbf": 0,
        "444bf": 0,
        "555bf": 0,
        "clock": 0,
        "minx": 0,
        "pyram": 0,
        "skewb": 0,
        "sq1": 0
      }
    },
    {
      "actualRank": 1363,
      "personId": "2022NGUY63",
      "personName": "Lê Trí Nguyên",
      "avgKinchScore": 3.1692671478323056,
      "kinchScore": {
        "222": 25.989672977624785,
        "333": 27.887868535524408,
        "444": 0,
        "555": 0,
        "666": 0,
        "777": 0,
        "333oh": 0,
        "333bf": 0,
        "333fm": 0,
        "333mbf": 0,
        "444bf": 0,
        "555bf": 0,
        "clock": 0,
        "minx": 0,
        "pyram": 0,
        "skewb": 0,
        "sq1": 0
      }
    },
    {
      "actualRank": 1364,
      "personId": "2020MINH06",
      "personName": "Phạm Bá Nhật Minh",
      "avgKinchScore": 3.167871618668071,
      "kinchScore": {
        "222": 0,
        "333": 26.84969753373662,
        "444": 0,
        "555": 0,
        "666": 0,
        "777": 0,
        "333oh": 0,
        "333bf": 0,
        "333fm": 0,
        "333mbf": 0,
        "444bf": 0,
        "555bf": 0,
        "clock": 0,
        "minx": 0,
        "pyram": 16.864111498257838,
        "skewb": 10.140008485362749,
        "sq1": 0
      }
    },
    {
      "actualRank": 1365,
      "personId": "2018VIET01",
      "personName": "Hà Đức Việt",
      "avgKinchScore": 3.164574843399091,
      "kinchScore": {
        "222": 18.55036855036855,
        "333": 35.247403787416005,
        "444": 0,
        "555": 0,
        "666": 0,
        "777": 0,
        "333oh": 0,
        "333bf": 0,
        "333fm": 0,
        "333mbf": 0,
        "444bf": 0,
        "555bf": 0,
        "clock": 0,
        "minx": 0,
        "pyram": 0,
        "skewb": 0,
        "sq1": 0
      }
    },
    {
      "actualRank": 1366,
      "personId": "2022ANDO02",
      "personName": "Đoàn Nguyễn Bảo An",
      "avgKinchScore": 3.162105831616494,
      "kinchScore": {
        "222": 23.59375,
        "333": 30.162049137480395,
        "444": 0,
        "555": 0,
        "666": 0,
        "777": 0,
        "333oh": 0,
        "333bf": 0,
        "333fm": 0,
        "333mbf": 0,
        "444bf": 0,
        "555bf": 0,
        "clock": 0,
        "minx": 0,
        "pyram": 0,
        "skewb": 0,
        "sq1": 0
      }
    },
    {
      "actualRank": 1367,
      "personId": "2025DUCN01",
      "personName": "Nguyễn Anh Đức",
      "avgKinchScore": 3.1614261573080626,
      "kinchScore": {
        "222": 18.170878459687124,
        "333": 35.57336621454994,
        "444": 0,
        "555": 0,
        "666": 0,
        "777": 0,
        "333oh": 0,
        "333bf": 0,
        "333fm": 0,
        "333mbf": 0,
        "444bf": 0,
        "555bf": 0,
        "clock": 0,
        "minx": 0,
        "pyram": 0,
        "skewb": 0,
        "sq1": 0
      }
    },
    {
      "actualRank": 1368,
      "personId": "2016NGHI04",
      "personName": "Vũ Hồng Trọng Nghĩa",
      "avgKinchScore": 3.155652772768994,
      "kinchScore": {
        "222": 19.483870967741936,
        "333": 34.162226169330964,
        "444": 0,
        "555": 0,
        "666": 0,
        "777": 0,
        "333oh": 0,
        "333bf": 0,
        "333fm": 0,
        "333mbf": 0,
        "444bf": 0,
        "555bf": 0,
        "clock": 0,
        "minx": 0,
        "pyram": 0,
        "skewb": 0,
        "sq1": 0
      }
    },
    {
      "actualRank": 1369,
      "personId": "2018LONG02",
      "personName": "Ngô Bảo Long",
      "avgKinchScore": 3.1536936941706073,
      "kinchScore": {
        "222": 0,
        "333": 25.407309555261996,
        "444": 28.20548324563833,
        "555": 0,
        "666": 0,
        "777": 0,
        "333oh": 0,
        "333bf": 0,
        "333fm": 0,
        "333mbf": 0,
        "444bf": 0,
        "555bf": 0,
        "clock": 0,
        "minx": 0,
        "pyram": 0,
        "skewb": 0,
        "sq1": 0
      }
    },
    {
      "actualRank": 1370,
      "personId": "2010DUON03",
      "personName": "Trong Duy Duong",
      "avgKinchScore": 3.147651304172424,
      "kinchScore": {
        "222": 0,
        "333": 28.649453823237337,
        "444": 0,
        "555": 0,
        "666": 0,
        "777": 0,
        "333oh": 24.860618347693865,
        "333bf": 0,
        "333fm": 0,
        "333mbf": 0,
        "444bf": 0,
        "555bf": 0,
        "clock": 0,
        "minx": 0,
        "pyram": 0,
        "skewb": 0,
        "sq1": 0
      }
    },
    {
      "actualRank": 1371,
      "personId": "2022HIEP01",
      "personName": "Trần Văn Hiệp",
      "avgKinchScore": 3.147343914915141,
      "kinchScore": {
        "222": 23.93026941362916,
        "333": 29.574577139928245,
        "444": 0,
        "555": 0,
        "666": 0,
        "777": 0,
        "333oh": 0,
        "333bf": 0,
        "333fm": 0,
        "333mbf": 0,
        "444bf": 0,
        "555bf": 0,
        "clock": 0,
        "minx": 0,
        "pyram": 0,
        "skewb": 0,
        "sq1": 0
      }
    },
    {
      "actualRank": 1372,
      "personId": "2022HUYN05",
      "personName": "Nguyễn Lâm Quốc Huy",
      "avgKinchScore": 3.147268297882967,
      "kinchScore": {
        "222": 21.695402298850574,
        "333": 31.808158765159867,
        "444": 0,
        "555": 0,
        "666": 0,
        "777": 0,
        "333oh": 0,
        "333bf": 0,
        "333fm": 0,
        "333mbf": 0,
        "444bf": 0,
        "555bf": 0,
        "clock": 0,
        "minx": 0,
        "pyram": 0,
        "skewb": 0,
        "sq1": 0
      }
    },
    {
      "actualRank": 1373,
      "personId": "2025VIET01",
      "personName": "Mai Nam Viet",
      "avgKinchScore": 3.146987347724308,
      "kinchScore": {
        "222": 0,
        "333": 17.919254658385093,
        "444": 0,
        "555": 0,
        "666": 0,
        "777": 0,
        "333oh": 0,
        "333bf": 0,
        "333fm": 0,
        "333mbf": 0,
        "444bf": 0,
        "555bf": 0,
        "clock": 0,
        "minx": 0,
        "pyram": 16.701173222912352,
        "skewb": 18.878357030015795,
        "sq1": 0
      }
    },
    {
      "actualRank": 1374,
      "personId": "2022KHOI04",
      "personName": "Nguyễn Duy Khôi",
      "avgKinchScore": 3.140316712175632,
      "kinchScore": {
        "222": 15.663900414937759,
        "333": 21.089181286549707,
        "444": 0,
        "555": 0,
        "666": 0,
        "777": 0,
        "333oh": 0,
        "333bf": 0,
        "333fm": 0,
        "333mbf": 0,
        "444bf": 0,
        "555bf": 0,
        "clock": 0,
        "minx": 0,
        "pyram": 16.63230240549828,
        "skewb": 0,
        "sq1": 0
      }
    },
    {
      "actualRank": 1375,
      "personId": "2022ANHL03",
      "personName": "Lê Gia Đức Anh",
      "avgKinchScore": 3.1368924649342174,
      "kinchScore": {
        "222": 0,
        "333": 53.3271719038817,
        "444": 0,
        "555": 0,
        "666": 0,
        "777": 0,
        "333oh": 0,
        "333bf": 0,
        "333fm": 0,
        "333mbf": 0,
        "444bf": 0,
        "555bf": 0,
        "clock": 0,
        "minx": 0,
        "pyram": 0,
        "skewb": 0,
        "sq1": 0
      }
    },
    {
      "actualRank": 1376,
      "personId": "2011TRAN07",
      "personName": "Trần Việt Cường",
      "avgKinchScore": 3.1343185563900797,
      "kinchScore": {
        "222": 0,
        "333": 29.259634888438136,
        "444": 0,
        "555": 0,
        "666": 0,
        "777": 0,
        "333oh": 0,
        "333bf": 0,
        "333fm": 0,
        "333mbf": 0,
        "444bf": 0,
        "555bf": 0,
        "clock": 0,
        "minx": 24.023780570193217,
        "pyram": 0,
        "skewb": 0,
        "sq1": 0
      }
    },
    {
      "actualRank": 1377,
      "personId": "2018NHIP01",
      "personName": "Phạm Yến Nhi",
      "avgKinchScore": 3.1301551752501986,
      "kinchScore": {
        "222": 0,
        "333": 29.378818737270873,
        "444": 0,
        "555": 0,
        "666": 0,
        "777": 0,
        "333oh": 23.833819241982507,
        "333bf": 0,
        "333fm": 0,
        "333mbf": 0,
        "444bf": 0,
        "555bf": 0,
        "clock": 0,
        "minx": 0,
        "pyram": 0,
        "skewb": 0,
        "sq1": 0
      }
    },
    {
      "actualRank": 1378,
      "personId": "2024TIEN03",
      "personName": "Trần Nhật Tiến",
      "avgKinchScore": 3.1296180918978456,
      "kinchScore": {
        "222": 23.08868501529052,
        "333": 30.114822546972857,
        "444": 0,
        "555": 0,
        "666": 0,
        "777": 0,
        "333oh": 0,
        "333bf": 0,
        "333fm": 0,
        "333mbf": 0,
        "444bf": 0,
        "555bf": 0,
        "clock": 0,
        "minx": 0,
        "pyram": 0,
        "skewb": 0,
        "sq1": 0
      }
    },
    {
      "actualRank": 1379,
      "personId": "2022KHAN26",
      "personName": "Nguyễn Bá Khang",
      "avgKinchScore": 3.1110152585323774,
      "kinchScore": {
        "222": 0,
        "333": 52.887259395050414,
        "444": 0,
        "555": 0,
        "666": 0,
        "777": 0,
        "333oh": 0,
        "333bf": 0,
        "333fm": 0,
        "333mbf": 0,
        "444bf": 0,
        "555bf": 0,
        "clock": 0,
        "minx": 0,
        "pyram": 0,
        "skewb": 0,
        "sq1": 0
      }
    },
    {
      "actualRank": 1379,
      "personId": "2022VUNG02",
      "personName": "Nguyễn Minh Vũ",
      "avgKinchScore": 3.1110152585323774,
      "kinchScore": {
        "222": 0,
        "333": 52.887259395050414,
        "444": 0,
        "555": 0,
        "666": 0,
        "777": 0,
        "333oh": 0,
        "333bf": 0,
        "333fm": 0,
        "333mbf": 0,
        "444bf": 0,
        "555bf": 0,
        "clock": 0,
        "minx": 0,
        "pyram": 0,
        "skewb": 0,
        "sq1": 0
      }
    },
    {
      "actualRank": 1381,
      "personId": "2017BAON09",
      "personName": "Nguyễn Hoàng Gia Bảo",
      "avgKinchScore": 3.104427785306091,
      "kinchScore": {
        "222": 21.089385474860336,
        "333": 31.685886875343215,
        "444": 0,
        "555": 0,
        "666": 0,
        "777": 0,
        "333oh": 0,
        "333bf": 0,
        "333fm": 0,
        "333mbf": 0,
        "444bf": 0,
        "555bf": 0,
        "clock": 0,
        "minx": 0,
        "pyram": 0,
        "skewb": 0,
        "sq1": 0
      }
    },
    {
      "actualRank": 1382,
      "personId": "2024DUCL01",
      "personName": "Lê Đỗ Quang Đức",
      "avgKinchScore": 3.0868970806358194,
      "kinchScore": {
        "222": 22.14076246334311,
        "333": 30.336487907465827,
        "444": 0,
        "555": 0,
        "666": 0,
        "777": 0,
        "333oh": 0,
        "333bf": 0,
        "333fm": 0,
        "333mbf": 0,
        "444bf": 0,
        "555bf": 0,
        "clock": 0,
        "minx": 0,
        "pyram": 0,
        "skewb": 0,
        "sq1": 0
      }
    },
    {
      "actualRank": 1383,
      "personId": "2024DUON02",
      "personName": "Đỗ Tùng Dương",
      "avgKinchScore": 3.0854471377969626,
      "kinchScore": {
        "222": 22.740963855421686,
        "333": 29.711637487126673,
        "444": 0,
        "555": 0,
        "666": 0,
        "777": 0,
        "333oh": 0,
        "333bf": 0,
        "333fm": 0,
        "333mbf": 0,
        "444bf": 0,
        "555bf": 0,
        "clock": 0,
        "minx": 0,
        "pyram": 0,
        "skewb": 0,
        "sq1": 0
      }
    },
    {
      "actualRank": 1384,
      "personId": "2015ANNG02",
      "personName": "Nguyễn Ngọc Thiên Ân",
      "avgKinchScore": 3.0837374561866806,
      "kinchScore": {
        "222": 31.991525423728813,
        "333": 20.43201133144476,
        "444": 0,
        "555": 0,
        "666": 0,
        "777": 0,
        "333oh": 0,
        "333bf": 0,
        "333fm": 0,
        "333mbf": 0,
        "444bf": 0,
        "555bf": 0,
        "clock": 0,
        "minx": 0,
        "pyram": 0,
        "skewb": 0,
        "sq1": 0
      }
    },
    {
      "actualRank": 1385,
      "personId": "2010NGUY12",
      "personName": "Hoang Nguyen",
      "avgKinchScore": 3.0825093122594076,
      "kinchScore": {
        "222": 14.178403755868544,
        "333": 21.667292527224934,
        "444": 0,
        "555": 0,
        "666": 0,
        "777": 0,
        "333oh": 16.556962025316455,
        "333bf": 0,
        "333fm": 0,
        "333mbf": 0,
        "444bf": 0,
        "555bf": 0,
        "clock": 0,
        "minx": 0,
        "pyram": 0,
        "skewb": 0,
        "sq1": 0
      }
    },
    {
      "actualRank": 1386,
      "personId": "2010NGUY29",
      "personName": "Hoang Son Nguyen",
      "avgKinchScore": 3.078405298906307,
      "kinchScore": {
        "222": 0,
        "333": 32.802728823195,
        "444": 0,
        "555": 0,
        "666": 0,
        "777": 0,
        "333oh": 19.53016125821222,
        "333bf": 0,
        "333fm": 0,
        "333mbf": 0,
        "444bf": 0,
        "555bf": 0,
        "clock": 0,
        "minx": 0,
        "pyram": 0,
        "skewb": 0,
        "sq1": 0
      }
    },
    {
      "actualRank": 1387,
      "personId": "2014THNH01",
      "personName": "Trần Quang Thái Thịnh",
      "avgKinchScore": 3.0777487801621857,
      "kinchScore": {
        "222": 21.695402298850574,
        "333": 30.626326963906582,
        "444": 0,
        "555": 0,
        "666": 0,
        "777": 0,
        "333oh": 0,
        "333bf": 0,
        "333fm": 0,
        "333mbf": 0,
        "444bf": 0,
        "555bf": 0,
        "clock": 0,
        "minx": 0,
        "pyram": 0,
        "skewb": 0,
        "sq1": 0
      }
    },
    {
      "actualRank": 1388,
      "personId": "2024TUEN01",
      "personName": "Nguyen Minh Tue",
      "avgKinchScore": 3.07436996362529,
      "kinchScore": {
        "222": 0,
        "333": 29.66580976863753,
        "444": 0,
        "555": 0,
        "666": 0,
        "777": 0,
        "333oh": 22.5984796129924,
        "333bf": 0,
        "333fm": 0,
        "333mbf": 0,
        "444bf": 0,
        "555bf": 0,
        "clock": 0,
        "minx": 0,
        "pyram": 0,
        "skewb": 0,
        "sq1": 0
      }
    },
    {
      "actualRank": 1389,
      "personId": "2024KHUE01",
      "personName": "Nguyen Minh Khue",
      "avgKinchScore": 3.0700904611459428,
      "kinchScore": {
        "222": 19.92084432717678,
        "333": 32.27069351230425,
        "444": 0,
        "555": 0,
        "666": 0,
        "777": 0,
        "333oh": 0,
        "333bf": 0,
        "333fm": 0,
        "333mbf": 0,
        "444bf": 0,
        "555bf": 0,
        "clock": 0,
        "minx": 0,
        "pyram": 0,
        "skewb": 0,
        "sq1": 0
      }
    },
    {
      "actualRank": 1390,
      "personId": "2019HAOP01",
      "personName": "Phan Nhật Hào",
      "avgKinchScore": 3.0699880612893757,
      "kinchScore": {
        "222": 17.198177676537586,
        "333": 15.30098117210289,
        "444": 0,
        "555": 0,
        "666": 0,
        "777": 0,
        "333oh": 0,
        "333bf": 0,
        "333fm": 0,
        "333mbf": 0,
        "444bf": 0,
        "555bf": 0,
        "clock": 0,
        "minx": 0,
        "pyram": 13.649182177100958,
        "skewb": 6.041456016177958,
        "sq1": 0
      }
    },
    {
      "actualRank": 1391,
      "personId": "2010PHAT01",
      "personName": "Chau Hong Phat",
      "avgKinchScore": 3.0686519842655002,
      "kinchScore": {
        "222": 0,
        "333": 29.12670368500757,
        "444": 23.040380047505938,
        "555": 0,
        "666": 0,
        "777": 0,
        "333oh": 0,
        "333bf": 0,
        "333fm": 0,
        "333mbf": 0,
        "444bf": 0,
        "555bf": 0,
        "clock": 0,
        "minx": 0,
        "pyram": 0,
        "skewb": 0,
        "sq1": 0
      }
    },
    {
      "actualRank": 1392,
      "personId": "2024DUCN02",
      "personName": "Nguyễn Tuấn Mạnh Đức",
      "avgKinchScore": 3.0675030016277907,
      "kinchScore": {
        "222": 21.602288984263232,
        "333": 30.54526204340921,
        "444": 0,
        "555": 0,
        "666": 0,
        "777": 0,
        "333oh": 0,
        "333bf": 0,
        "333fm": 0,
        "333mbf": 0,
        "444bf": 0,
        "555bf": 0,
        "clock": 0,
        "minx": 0,
        "pyram": 0,
        "skewb": 0,
        "sq1": 0
      }
    },
    {
      "actualRank": 1393,
      "personId": "2023KHAN49",
      "personName": "Nguyễn An Khánh",
      "avgKinchScore": 3.066216314164983,
      "kinchScore": {
        "222": 11.218424962852898,
        "333": 18.31746031746032,
        "444": 0,
        "555": 0,
        "666": 0,
        "777": 0,
        "333oh": 0,
        "333bf": 0,
        "333fm": 0,
        "333mbf": 0,
        "444bf": 0,
        "555bf": 0,
        "clock": 0,
        "minx": 0,
        "pyram": 0,
        "skewb": 22.589792060491494,
        "sq1": 0
      }
    },
    {
      "actualRank": 1394,
      "personId": "2015TUAN01",
      "personName": "Nguyễn Anh Tuấn",
      "avgKinchScore": 3.0630273600144475,
      "kinchScore": {
        "222": 28.330206378986865,
        "333": 0,
        "444": 23.74125874125874,
        "555": 0,
        "666": 0,
        "777": 0,
        "333oh": 0,
        "333bf": 0,
        "333fm": 0,
        "333mbf": 0,
        "444bf": 0,
        "555bf": 0,
        "clock": 0,
        "minx": 0,
        "pyram": 0,
        "skewb": 0,
        "sq1": 0
      }
    },
    {
      "actualRank": 1395,
      "personId": "2015BINH01",
      "personName": "Lê Trần Thái Bình",
      "avgKinchScore": 3.0608909725174414,
      "kinchScore": {
        "222": 17.933491686460805,
        "333": 34.1016548463357,
        "444": 0,
        "555": 0,
        "666": 0,
        "777": 0,
        "333oh": 0,
        "333bf": 0,
        "333fm": 0,
        "333mbf": 0,
        "444bf": 0,
        "555bf": 0,
        "clock": 0,
        "minx": 0,
        "pyram": 0,
        "skewb": 0,
        "sq1": 0
      }
    },
    {
      "actualRank": 1396,
      "personId": "2024HIEN02",
      "personName": "Thái Minh Hiển",
      "avgKinchScore": 3.0601181833588127,
      "kinchScore": {
        "222": 22.98325722983257,
        "333": 29.03875188726724,
        "444": 0,
        "555": 0,
        "666": 0,
        "777": 0,
        "333oh": 0,
        "333bf": 0,
        "333fm": 0,
        "333mbf": 0,
        "444bf": 0,
        "555bf": 0,
        "clock": 0,
        "minx": 0,
        "pyram": 0,
        "skewb": 0,
        "sq1": 0
      }
    },
    {
      "actualRank": 1397,
      "personId": "2022HIEU05",
      "personName": "Đặng Xuân Minh Hiếu",
      "avgKinchScore": 3.0599748249139047,
      "kinchScore": {
        "222": 19.383825417201543,
        "333": 32.63574660633484,
        "444": 0,
        "555": 0,
        "666": 0,
        "777": 0,
        "333oh": 0,
        "333bf": 0,
        "333fm": 0,
        "333mbf": 0,
        "444bf": 0,
        "555bf": 0,
        "clock": 0,
        "minx": 0,
        "pyram": 0,
        "skewb": 0,
        "sq1": 0
      }
    },
    {
      "actualRank": 1398,
      "personId": "2019NHAN01",
      "personName": "Nguyễn Doãn Nhân",
      "avgKinchScore": 3.05776364599894,
      "kinchScore": {
        "222": 0,
        "333": 51.98198198198198,
        "444": 0,
        "555": 0,
        "666": 0,
        "777": 0,
        "333oh": 0,
        "333bf": 0,
        "333fm": 0,
        "333mbf": 0,
        "444bf": 0,
        "555bf": 0,
        "clock": 0,
        "minx": 0,
        "pyram": 0,
        "skewb": 0,
        "sq1": 0
      }
    },
    {
      "actualRank": 1399,
      "personId": "2016HUYD01",
      "personName": "Đinh Gia Huy",
      "avgKinchScore": 3.054092993874168,
      "kinchScore": {
        "222": 20.268456375838927,
        "333": 31.651124520021938,
        "444": 0,
        "555": 0,
        "666": 0,
        "777": 0,
        "333oh": 0,
        "333bf": 0,
        "333fm": 0,
        "333mbf": 0,
        "444bf": 0,
        "555bf": 0,
        "clock": 0,
        "minx": 0,
        "pyram": 0,
        "skewb": 0,
        "sq1": 0
      }
    },
    {
      "actualRank": 1400,
      "personId": "2022SANG06",
      "personName": "Phạm Tấn Sang",
      "avgKinchScore": 3.0519322735440633,
      "kinchScore": {
        "222": 0,
        "333": 32.27069351230425,
        "444": 0,
        "555": 0,
        "666": 0,
        "777": 0,
        "333oh": 19.61215513794482,
        "333bf": 0,
        "333fm": 0,
        "333mbf": 0,
        "444bf": 0,
        "555bf": 0,
        "clock": 0,
        "minx": 0,
        "pyram": 0,
        "skewb": 0,
        "sq1": 0
      }
    }
  ]
}